LICENSE
MANIFEST.in
README.md
setup.py
django_exceptional_middleware.egg-info/PKG-INFO
django_exceptional_middleware.egg-info/SOURCES.txt
django_exceptional_middleware.egg-info/dependency_links.txt
django_exceptional_middleware.egg-info/top_level.txt
exceptional_middleware/__init__.py
exceptional_middleware/middleware.py
exceptional_middleware/models.py
exceptional_middleware/responses.py
exceptional_middleware/templates/http_responses/default.html