Metadata-Version: 1.0
Name: django-exceptional-middleware
Version: 0.9
Summary: Django middleware to allow generating arbitrary HTTP status codes via exceptions.
Home-page: http://tartarus.org/james/computers/django/
Author: James Aylett
Author-email: UNKNOWN
License: MIT
Platform: UNKNOWN
